sator_app/__init__.py
sator_app/bootstrap/__init__.py
sator_app/bootstrap/analysis.py
sator_app/bootstrap/annotation.py
sator_app/bootstrap/base.py
sator_app/bootstrap/extraction.py
sator_app/bootstrap/resolution.py
sator_app/services/__init__.py
sator_app/services/orchestration/__init__.py
sator_app/services/orchestration/processing.py
sator_app/services/processing/__init__.py
sator_app/services/processing/patch.py
sator_app/services/processing/product.py
sator_app/services/processing/vulnerability.py
sator_app-0.0.15.dist-info/licenses/LICENSE
sator_app-0.0.15.dist-info/METADATA
sator_app-0.0.15.dist-info/WHEEL
sator_app-0.0.15.dist-info/top_level.txt
sator_app-0.0.15.dist-info/RECORD
